quickEDA/__init__.py
quickEDA/__main__.py
quickEDA/dataframe.py
quickEDA-0.2.dist-info/LICENSE.txt
quickEDA-0.2.dist-info/METADATA
quickEDA-0.2.dist-info/WHEEL
quickEDA-0.2.dist-info/entry_points.txt
quickEDA-0.2.dist-info/top_level.txt
quickEDA-0.2.dist-info/RECORD
