Metadata-Version: 2.1
Name: quickEDA
Version: 0.2
Summary: All data analysis performed in single line of code
Home-page: https://github.com/Reshmamk1604/DSprojects/quickEDA
Author: Reshma M K
Author-email: mahdeeyafarha@gmail.com
License: MIT
Keywords: EDA eda exploratory data analysis data preprocessing
Platform: UNKNOWN
Classifier: License :: OSI Approved :: MIT License
Classifier: Programming Language :: Python :: 3
Classifier: Programming Language :: Python :: 3.6
Classifier: Programming Language :: Python :: 3.7
Classifier: Programming Language :: Python :: 3.8
Classifier: Programming Language :: Python :: 3.9
Classifier: Operating System :: OS Independent
License-File: LICENSE.txt
